pypi/__init__.py
pypi/matrix_add.py
pypi/test.py
PYPItest_bear-0.0.1.dist-info/LICENSE
PYPItest_bear-0.0.1.dist-info/METADATA
PYPItest_bear-0.0.1.dist-info/WHEEL
PYPItest_bear-0.0.1.dist-info/top_level.txt
PYPItest_bear-0.0.1.dist-info/RECORD
